[
  {
    "timestamp": "2025-09-08T15:11:21.780Z",
    "userAgent": "Mozilla/5.0 (Macintosh; Intel Mac OS X 10_15_7) AppleWebKit/605.1.15 (KHTML, like Gecko) Version/18.6 Safari/605.1.15",
    "referrer": "direct",
    "pathname": "/",
    "screenResolution": "2056x1329",
    "language": "en-US",
    "timezone": "Africa/Johannesburg",
    "sessionId": "mfb9eu24fwxbdnolp9n",
    "event": "page_view",
    "pageName": "Altus Rossouw - Embedded Systems Developer & IoT Specialist",
    "ip": "::1",
    "country": "Unknown"
  },
  {
    "timestamp": "2025-09-08T15:11:21.772Z",
    "userAgent": "Mozilla/5.0 (Macintosh; Intel Mac OS X 10_15_7) AppleWebKit/605.1.15 (KHTML, like Gecko) Version/18.6 Safari/605.1.15",
    "referrer": "direct",
    "pathname": "/",
    "screenResolution": "2056x1329",
    "language": "en-US",
    "timezone": "Africa/Johannesburg",
    "sessionId": "mfb9eu24fwxbdnolp9n",
    "event": "page_view",
    "pageName": "Altus Rossouw - Embedded Systems Developer & IoT Specialist",
    "ip": "::1",
    "country": "Unknown"
  },
  {
    "timestamp": "2025-09-08T15:22:40.082Z",
    "userAgent": "Mozilla/5.0 (Macintosh; Intel Mac OS X 10_15_7) AppleWebKit/605.1.15 (KHTML, like Gecko) Version/18.6 Safari/605.1.15",
    "referrer": "direct",
    "pathname": "/",
    "screenResolution": "2056x1329",
    "language": "en-US",
    "timezone": "Africa/Johannesburg",
    "sessionId": "mfb9tdfuo0clu75xdhi",
    "event": "page_view",
    "pageName": "Altus Rossouw - Embedded Systems Developer & IoT Specialist",
    "ip": "::1",
    "country": "Unknown"
  },
  {
    "timestamp": "2025-09-08T15:22:40.074Z",
    "userAgent": "Mozilla/5.0 (Macintosh; Intel Mac OS X 10_15_7) AppleWebKit/605.1.15 (KHTML, like Gecko) Version/18.6 Safari/605.1.15",
    "referrer": "direct",
    "pathname": "/",
    "screenResolution": "2056x1329",
    "language": "en-US",
    "timezone": "Africa/Johannesburg",
    "sessionId": "mfb9tdfuo0clu75xdhi",
    "event": "page_view",
    "pageName": "Altus Rossouw - Embedded Systems Developer & IoT Specialist",
    "ip": "::1",
    "country": "Unknown"
  },
  {
    "timestamp": "2025-09-08T15:27:48.461Z",
    "userAgent": "Mozilla/5.0 (Macintosh; Intel Mac OS X 10_15_7) AppleWebKit/605.1.15 (KHTML, like Gecko) Version/18.6 Safari/605.1.15",
    "referrer": "direct",
    "pathname": "/",
    "screenResolution": "2056x1329",
    "language": "en-US",
    "timezone": "Africa/Johannesburg",
    "sessionId": "mfb9zzdxxw584borka",
    "event": "page_view",
    "pageName": "Altus Rossouw - Embedded Systems Developer & IoT Specialist",
    "ip": "::1",
    "country": "Unknown"
  },
  {
    "timestamp": "2025-09-08T15:27:48.453Z",
    "userAgent": "Mozilla/5.0 (Macintosh; Intel Mac OS X 10_15_7) AppleWebKit/605.1.15 (KHTML, like Gecko) Version/18.6 Safari/605.1.15",
    "referrer": "direct",
    "pathname": "/",
    "screenResolution": "2056x1329",
    "language": "en-US",
    "timezone": "Africa/Johannesburg",
    "sessionId": "mfb9zzdxxw584borka",
    "event": "page_view",
    "pageName": "Altus Rossouw - Embedded Systems Developer & IoT Specialist",
    "ip": "::1",
    "country": "Unknown"
  },
  {
    "timestamp": "2025-09-08T15:32:00.852Z",
    "userAgent": "Mozilla/5.0 (Macintosh; Intel Mac OS X 10_15_7) AppleWebKit/605.1.15 (KHTML, like Gecko) Version/18.6 Safari/605.1.15",
    "referrer": "direct",
    "pathname": "/",
    "screenResolution": "2056x1329",
    "language": "en-US",
    "timezone": "Africa/Johannesburg",
    "sessionId": "mfba5e50k7nde2yd1zp",
    "event": "page_view",
    "pageName": "Altus Rossouw - Embedded Systems Developer & IoT Specialist",
    "ip": "::1",
    "country": "Unknown"
  },
  {
    "timestamp": "2025-09-08T15:32:00.854Z",
    "userAgent": "Mozilla/5.0 (Macintosh; Intel Mac OS X 10_15_7) AppleWebKit/605.1.15 (KHTML, like Gecko) Version/18.6 Safari/605.1.15",
    "referrer": "direct",
    "pathname": "/",
    "screenResolution": "2056x1329",
    "language": "en-US",
    "timezone": "Africa/Johannesburg",
    "sessionId": "mfba5e50k7nde2yd1zp",
    "event": "page_view",
    "pageName": "Altus Rossouw - Embedded Systems Developer & IoT Specialist",
    "ip": "::1",
    "country": "Unknown"
  }
]